g3w_admin_processing-1.2.1b1.dev1.dist-info/licenses/LICENSE
qprocessing/__init__.py
qprocessing/admin.py
qprocessing/apiurls.py
qprocessing/apps.py
qprocessing/configs.py
qprocessing/forms.py
qprocessing/models.py
qprocessing/receivers.py
qprocessing/sitetrees.py
qprocessing/tasks.py
qprocessing/urls.py
qprocessing/views.py
qprocessing/api/__init__.py
qprocessing/api/permissions.py
qprocessing/api/views/__init__.py
qprocessing/api/views/actions.py
qprocessing/api/views/admin.py
qprocessing/api/views/models.py
qprocessing/api/views/upload.py
qprocessing/migrations/0001_initial.py
qprocessing/migrations/0002_auto_20230615_1609.py
qprocessing/migrations/0003_qprocessinginputupload.py
qprocessing/migrations/0004_auto_20230809_0920.py
qprocessing/migrations/0005_alter_qprocessinginputupload_user.py
qprocessing/migrations/__init__.py
qprocessing/static/qprocessing/js/plugin.js
qprocessing/static/qprocessing/js/components/DrawInputVectorFeatures.js
qprocessing/static/qprocessing/js/components/InputFieldChooser.js
qprocessing/static/qprocessing/js/components/InputPrjRasterLayer.js
qprocessing/static/qprocessing/js/components/InputPrjVectorLayer.js
qprocessing/static/qprocessing/js/components/ModelPanel.js
qprocessing/static/qprocessing/js/components/ModelResults.js
qprocessing/static/qprocessing/js/components/OutputFile.js
qprocessing/static/qprocessing/js/components/OutputRasterLayer.js
qprocessing/static/qprocessing/js/components/OutputVectorLayer.js
qprocessing/static/qprocessing/js/components/UploadVectorFile.js
qprocessing/static/qprocessing/js/i18n/en.js
qprocessing/static/qprocessing/js/i18n/index.js
qprocessing/static/qprocessing/js/i18n/it.js
qprocessing/templates/qprocessing/project_form.html
qprocessing/templates/qprocessing/projects_list.html
qprocessing/tests/__init__.py
qprocessing/tests/base.py
qprocessing/tests/test_algorithm.py
qprocessing/tests/test_api.py
qprocessing/tests/test_api_models.py
qprocessing/tests/data/qprocessing_qprocessing.qgs
qprocessing/tests/data/qprocessing_qprocessing_attachments.zip
g3w_admin_processing-1.2.1b1.dev1.dist-info/METADATA
g3w_admin_processing-1.2.1b1.dev1.dist-info/WHEEL
g3w_admin_processing-1.2.1b1.dev1.dist-info/top_level.txt
g3w_admin_processing-1.2.1b1.dev1.dist-info/RECORD
