Metadata-Version: 2.4
Name: g3w-admin-processing
Version: 1.2.1b1.dev1
Summary: G3W-ADMIN plugin for use the processing features of QGIS application-
Author-email: Gis3w snc <info@gis3w.it>
License: Mozilla Public License 2.0 (MPL 2.0)
Project-URL: Homepage, https://github.com/g3w-suite/g3w-admin-processing
Project-URL: Bug Tracker, https://github.com/g3w-suite/g3w-admin-processing/issues
Classifier: Development Status :: 4 - Beta
Classifier: Environment :: Web Environment
Classifier: Framework :: Django
Classifier: Intended Audience :: Developers
Classifier: License :: OSI Approved :: Mozilla Public License 2.0 (MPL 2.0)
Classifier: Operating System :: OS Independent
Classifier: Programming Language :: Python :: 3
Classifier: Topic :: Software Development :: Libraries
License-File: LICENSE
Requires-Dist: cryptography==3.4.8
Provides-Extra: dev
Dynamic: license-file
